bambo/__init__.py
bambo/cli.py
bambo/core.py
bambo/monitor.py
bambo/urls.txt
bambo-2.0.0.dist-info/LICENSE
bambo-2.0.0.dist-info/METADATA
bambo-2.0.0.dist-info/WHEEL
bambo-2.0.0.dist-info/entry_points.txt
bambo-2.0.0.dist-info/RECORD
