Metadata-Version: 2.1
Name: bambo
Version: 2.0.0
Summary: A lightweight and efficient tool for performing load testing on your HTTP and HTTPS services.
Author: Subham Singh
Author-email: geekysubham@gmail.com
Requires-Python: >=3.10,<4.0
Classifier: Programming Language :: Python :: 3
Classifier: Programming Language :: Python :: 3.10
Classifier: Programming Language :: Python :: 3.11
Classifier: Programming Language :: Python :: 3.12
Requires-Dist: prettytable (>=3.9.0,<4.0.0)
Requires-Dist: requests (>=2.31.0,<3.0.0)
